MANIFEST.in
README.rst
setup.cfg
setup.py
chatangobot/README.rst
chatangobot/__init__.py
chatangobot/utils.py
chatangobot/core/__init__.py
chatangobot/core/anonpm.py
chatangobot/core/channel.py
chatangobot/core/manager.py
chatangobot/core/message.py
chatangobot/core/pm.py
chatangobot/core/room.py
chatangobot/core/settings.py
chatangobot/core/user.py
fireh_runner/__init__.py
fireh_runner/fireh_runner.py
fireh_runner/modules/__init__.py
fireh_runner/modules/django.py
fireh_runner/modules/doxygen.py
fireh_runner/modules/pip.py
fireh_runner/modules/setup.py
fireh_runner/modules/uwsgi_django.py
fireh_runner/modules/waf.py
fireh_runner/setup_modules/__init__.py
fireh_runner/setup_modules/alembic.py
fireh_runner/setup_modules/bower.py
fireh_runner/setup_modules/git.py
fireh_runner/setup_modules/npm.py
fireh_runner/setup_modules/pybuildtool.py
fireh_runner/setup_modules/python.py
pychatangobot.egg-info/PKG-INFO
pychatangobot.egg-info/SOURCES.txt
pychatangobot.egg-info/dependency_links.txt
pychatangobot.egg-info/requires.txt
pychatangobot.egg-info/top_level.txt