Metadata-Version: 1.1
Name: pychatangobot
Version: 0.0.7
Summary: asyncio implementation of Chatango bot (ch.py).
Home-page: https://github.com/dozymoe/PyChatangoBot
Author: Fahri Reza
Author-email: dozymoe@gmail.com
License: MIT
Download-URL: https://github.com/dozymoe/PyChatangoBot/tarball/0.0.7
Platform: any
